asv_txt
