Metadata-Version: 1.0
Name: asv-txt
Version: dev-20110622-01
Summary: 
